{
  "base_input": [
    [
      [
        -3,
        -4,
        5
      ],
      3
    ],
    [
      [
        4,
        -4,
        4
      ],
      2
    ],
    [
      [
        -3,
        2,
        1,
        2,
        -1,
        -2,
        1
      ],
      1
    ],
    [
      [
        123,
        -123,
        20,
        0,
        1,
        2,
        -3
      ],
      3
    ],
    [
      [
        -123,
        20,
        0,
        1,
        2,
        -3
      ],
      4
    ],
    [
      [
        5,
        15,
        0,
        3,
        -13,
        -8,
        0
      ],
      7
    ],
    [
      [
        -1,
        0,
        2,
        5,
        3,
        -10
      ],
      2
    ],
    [
      [
        1,
        0,
        5,
        -7
      ],
      1
    ],
    [
      [
        4,
        -4
      ],
      2
    ],
    [
      [
        -10,
        10
      ],
      2
    ],
    [
      [
        1,
        2,
        3,
        -23,
        243,
        -400,
        0
      ],
      0
    ]
  ],
  "plus_input": [
    [
      [
        1,
        2,
        3,
        4,
        5
      ],
      3
    ],
    [
      [
        -2,
        5,
        4,
        10,
        3,
        8,
        3
      ],
      3
    ],
    [
      [
        1
      ],
      0
    ],
    [
      [
        1000,
        -1000
      ],
      2
    ],
    [
      [
        5,
        2,
        1
      ],
      1
    ]
  ],
  "atol": 0,
  "contract": "\n    assert type(arr) == list, \"invalid inputs\" # $_CONTRACT_$\n    assert 1 <= len(arr) <= 1000, \"invalid inputs\" # $_CONTRACT_$\n    assert all(-1000 <= x <= 1000 for x in arr), \"invalid inputs\" # $_CONTRACT_$\n    assert type(k) == int, \"invalid inputs\" # $_CONTRACT_$\n    assert 0 <= k <= len(arr), \"invalid inputs\" # $_CONTRACT_$\n",
  "entry_point": "maximum"
}